nitk/__init__.py
nitk/clime.py
nitk/correlation_permuter.py
nitk/d_trace.py
nitk/l2_penalized_estimator.py
nitk/methods.py
nitk/scaled_lasso.py
nitk/scio.py
nitk/space.py
topcorr/__init__.py
topcorr/topcorr.py
topcorr-0.18.dist-info/LICENSE
topcorr-0.18.dist-info/METADATA
topcorr-0.18.dist-info/WHEEL
topcorr-0.18.dist-info/top_level.txt
topcorr-0.18.dist-info/RECORD
