Metadata-Version: 2.1
Name: topcorr
Version: 0.18
Summary: A package for consutructing filtered correlation networks
Home-page: https://github.com/shazzzm/topcorr
Author: Tristan Millington
Author-email: tristan.millington@gmail.com
License: UNKNOWN
Platform: UNKNOWN
Classifier: Programming Language :: Python :: 3
Classifier: License :: OSI Approved :: GNU General Public License v3 (GPLv3)
Classifier: Operating System :: OS Independent
Classifier: Development Status :: 2 - Pre-Alpha
